ngit/__init__.py
ngit/console.py
ngit/ngit.py
ngit/repo_data.py
ngit-0.1.3.dist-info/licenses/LICENSE
ngit-0.1.3.dist-info/METADATA
ngit-0.1.3.dist-info/WHEEL
ngit-0.1.3.dist-info/entry_points.txt
ngit-0.1.3.dist-info/top_level.txt
ngit-0.1.3.dist-info/RECORD
