Metadata-Version: 2.4
Name: ngit
Version: 0.1.3
Summary: Custom Git wrapper CLI
Author: ja1codes
License-File: LICENSE
Requires-Dist: typer
Requires-Dist: gitpython
Requires-Dist: rich
Dynamic: license-file
